{
  "red": [
    {
      "path": "https://cdn.tag-walk.com/list/balmain-men-women-s20-vogue-2732x4098-014-90480e.jpg"
    },
    {
      "path": "https://cdn.tag-walk.com/list/25-0a4faa.jpg"
    },
    {
      "path": "https://cdn.tag-walk.com/list/27-5cd1d0.jpg"
    },
    {
      "path": "https://cdn.tag-walk.com/list/arias-resort-20-look9-d24d85.jpg"
    },
    {
      "path": "https://cdn.tag-walk.com/list/chloe-shanghai-s20-14-a74614.jpg"
    },
    {
      "path": "https://cdn.tag-walk.com/list/burberry-spring-summer-2020-pre-collection-look-18-2ee1db.jpg"
    },
    {
      "path": "https://cdn.tag-walk.com/list/aynilookbook0665-921013.jpg"
    },
    {
      "path": "https://cdn.tag-walk.com/list/35-14127f.png"
    },
    {
      "path": "https://cdn.tag-walk.com/list/look-11-34b85d.jpg"
    }
  ],
  "pastel": [
    {
      "path": "https://cdn.tag-walk.com/list/22-828f7a.jpg"
    },
    {
      "path": "https://cdn.tag-walk.com/list/49-be02fa.jpg"
    },
    {
      "path": "https://cdn.tag-walk.com/list/52-611878.jpg"
    },
    {
      "path": "https://cdn.tag-walk.com/list/aynilookbook0721-9822ba.jpg"
    }
  ],
  "coat": [
    {
      "path": "https://cdn.tag-walk.com/list/02-792742.jpg"
    },
    {
      "path": "https://cdn.tag-walk.com/list/11-caebdd.jpg"
    },
    {
      "path": "https://cdn.tag-walk.com/list/17-fe6d5e.jpg"
    },
    {
      "path": "https://cdn.tag-walk.com/list/19-596948.jpg"
    },
    {
      "path": "https://cdn.tag-walk.com/list/28-83cfa3.jpg"
    },
    {
      "path": "https://cdn.tag-walk.com/list/34-8491bf.jpg"
    },
    {
      "path": "https://cdn.tag-walk.com/list/altuzarra-ps20-look-04-fb1fca.jpg"
    },
    {
      "path": "https://cdn.tag-walk.com/list/altuzarra-ps20-look-11-5457f1.jpg"
    }
  ],
  "midi dress": [
    {
      "path": "https://cdn.tag-walk.com/list/altuzarra-ps20-look-10-4d205d.jpg"
    },
    {
      "path": "https://cdn.tag-walk.com/list/13-ea4e42.jpg"
    }
  ],
  "white": [
    {
      "path": "https://cdn.tag-walk.com/list/plim-ss20-womens-lookbook-04-321de3.jpg"
    }
  ]
}
